first_io/__init__.py
first_io/api_io.cpython-310-x86_64-linux-gnu.so
first_io/call_api_stream.py
first_io/file_io.cpython-310-x86_64-linux-gnu.so
first_io/ttte/src/dev/api/__init__.py
first_io/ttte/src/dev/api/app.py
first_io/ttte/src/dev/src/__init__.py
first_io/ttte/src/dev/src/main.py
first_io/ttte/src/dev/tests/test.py
first_io-0.1.9.dist-info/METADATA
first_io-0.1.9.dist-info/WHEEL
first_io-0.1.9.dist-info/top_level.txt
first_io-0.1.9.dist-info/RECORD
